{"gameId": "0042500116", "gameStatus": 3, "gameStatusText": "Final", "gameTimeUTC": "2026-05-01T00:00:00Z", "teams": [{"teamId": 1610612755, "tricode": "PHI", "wins": 3, "losses": 3, "q1": 20, "q2": 38, "q3": 24, "q4": 24, "score": 106, "isHome": true}, {"teamId": 1610612738, "tricode": "BOS", "wins": 3, "losses": 3, "q1": 23, "q2": 26, "q3": 14, "q4": 30, "score": 93, "isHome": false}], "teamStats": [{"teamId": 1610612755, "tricode": "PHI", "points": 106.0, "reboundsTotal": 48.0, "assists": 22.0, "steals": 7.0, "blocks": 6.0, "turnovers": 10.0, "fieldGoalsPercentage": 0.438, "threePointersPercentage": 0.333, "freeThrowsPercentage": 0.895, "pointsInThePaint": 40.0, "pointsFastBreak": 16.0, "benchPoints": 6.0, "biggestLead": 23.0, "leadChanges": 8.0, "timesTied": 3.0}, {"teamId": 1610612738, "tricode": "BOS", "points": 93.0, "reboundsTotal": 46.0, "assists": 18.0, "steals": 7.0, "blocks": 3.0, "turnovers": 13.0, "fieldGoalsPercentage": 0.419, "threePointersPercentage": 0.293, "freeThrowsPercentage": 0.563, "pointsInThePaint": 42.0, "pointsFastBreak": 14.0, "benchPoints": 38.0, "biggestLead": 5.0, "leadChanges": 8.0, "timesTied": 3.0}], "players": [{"personId": 1626162, "name": "Kelly Oubre Jr.", "teamId": 1610612755, "tricode": "PHI", "position": "F", "minutes": "38:44", "points": 14, "reboundsTotal": 9, "reboundsOffensive": 3, "reboundsDefensive": 6, "assists": 1, "steals": 2, "blocks": 2, "turnovers": 3, "foulsPersonal": 3, "fieldGoalsMade": 6, "fieldGoalsAttempted": 11, "fieldGoalsPercentage": 0.545, "threePointersMade": 1, "threePointersAttempted": 3, "threePointersPercentage": 0.333, "freeThrowsMade": 1, "freeThrowsAttempted": 2, "freeThrowsPercentage": 0.5, "plusMinusPoints": 23.0}, {"personId": 202331, "name": "Paul George", "teamId": 1610612755, "tricode": "PHI", "position": "F", "minutes": "39:37", "points": 23, "reboundsTotal": 4, "reboundsOffensive": 0, "reboundsDefensive": 4, "assists": 3, "steals": 2, "blocks": 1, "turnovers": 4, "foulsPersonal": 2, "fieldGoalsMade": 8, "fieldGoalsAttempted": 17, "fieldGoalsPercentage": 0.471, "threePointersMade": 5, "threePointersAttempted": 9, "threePointersPercentage": 0.556, "freeThrowsMade": 2, "freeThrowsAttempted": 2, "freeThrowsPercentage": 1.0, "plusMinusPoints": 11.0}, {"personId": 203954, "name": "Joel Embiid", "teamId": 1610612755, "tricode": "PHI", "position": "C", "minutes": "34:11", "points": 19, "reboundsTotal": 10, "reboundsOffensive": 1, "reboundsDefensive": 9, "assists": 8, "steals": 1, "blocks": 0, "turnovers": 1, "foulsPersonal": 2, "fieldGoalsMade": 6, "fieldGoalsAttempted": 18, "fieldGoalsPercentage": 0.333, "threePointersMade": 1, "threePointersAttempted": 5, "threePointersPercentage": 0.2, "freeThrowsMade": 6, "freeThrowsAttempted": 7, "freeThrowsPercentage": 0.857, "plusMinusPoints": 7.0}, {"personId": 1642845, "name": "VJ Edgecombe", "teamId": 1610612755, "tricode": "PHI", "position": "G", "minutes": "38:00", "points": 14, "reboundsTotal": 8, "reboundsOffensive": 0, "reboundsDefensive": 8, "assists": 3, "steals": 0, "blocks": 2, "turnovers": 0, "foulsPersonal": 3, "fieldGoalsMade": 5, "fieldGoalsAttempted": 11, "fieldGoalsPercentage": 0.455, "threePointersMade": 1, "threePointersAttempted": 6, "threePointersPercentage": 0.167, "freeThrowsMade": 3, "freeThrowsAttempted": 3, "freeThrowsPercentage": 1.0, "plusMinusPoints": 18.0}, {"personId": 1630178, "name": "Tyrese Maxey", "teamId": 1610612755, "tricode": "PHI", "position": "G", "minutes": "39:49", "points": 30, "reboundsTotal": 2, "reboundsOffensive": 1, "reboundsDefensive": 1, "assists": 5, "steals": 2, "blocks": 0, "turnovers": 0, "foulsPersonal": 1, "fieldGoalsMade": 11, "fieldGoalsAttempted": 22, "fieldGoalsPercentage": 0.5, "threePointersMade": 3, "threePointersAttempted": 5, "threePointersPercentage": 0.6, "freeThrowsMade": 5, "freeThrowsAttempted": 5, "freeThrowsPercentage": 1.0, "plusMinusPoints": 15.0}, {"personId": 1629656, "name": "Quentin Grimes", "teamId": 1610612755, "tricode": "PHI", "position": "", "minutes": "22:09", "points": 2, "reboundsTotal": 3, "reboundsOffensive": 1, "reboundsDefensive": 2, "assists": 2, "steals": 0, "blocks": 0, "turnovers": 0, "foulsPersonal": 0, "fieldGoalsMade": 1, "fieldGoalsAttempted": 6, "fieldGoalsPercentage": 0.167, "threePointersMade": 0, "threePointersAttempted": 3, "threePointersPercentage": 0.0, "freeThrowsMade": 0, "freeThrowsAttempted": 0, "freeThrowsPercentage": 0.0, "plusMinusPoints": 2.0}, {"personId": 203083, "name": "Andre Drummond", "teamId": 1610612755, "tricode": "PHI", "position": "", "minutes": "12:35", "points": 2, "reboundsTotal": 7, "reboundsOffensive": 1, "reboundsDefensive": 6, "assists": 0, "steals": 0, "blocks": 1, "turnovers": 0, "foulsPersonal": 2, "fieldGoalsMade": 1, "fieldGoalsAttempted": 1, "fieldGoalsPercentage": 1.0, "threePointersMade": 0, "threePointersAttempted": 0, "threePointersPercentage": 0.0, "freeThrowsMade": 0, "freeThrowsAttempted": 0, "freeThrowsPercentage": 0.0, "plusMinusPoints": 10.0}, {"personId": 1642348, "name": "Justin Edwards", "teamId": 1610612755, "tricode": "PHI", "position": "", "minutes": "10:00", "points": 2, "reboundsTotal": 5, "reboundsOffensive": 1, "reboundsDefensive": 4, "assists": 0, "steals": 0, "blocks": 0, "turnovers": 2, "foulsPersonal": 2, "fieldGoalsMade": 1, "fieldGoalsAttempted": 3, "fieldGoalsPercentage": 0.333, "threePointersMade": 0, "threePointersAttempted": 2, "threePointersPercentage": 0.0, "freeThrowsMade": 0, "freeThrowsAttempted": 0, "freeThrowsPercentage": 0.0, "plusMinusPoints": -5.0}, {"personId": 1630570, "name": "Trendon Watford", "teamId": 1610612755, "tricode": "PHI", "position": "", "minutes": "1:14", "points": 0, "reboundsTotal": 0, "reboundsOffensive": 0, "reboundsDefensive": 0, "assists": 0, "steals": 0, "blocks": 0, "turnovers": 0, "foulsPersonal": 0, "fieldGoalsMade": 0, "fieldGoalsAttempted": 0, "fieldGoalsPercentage": 0.0, "threePointersMade": 0, "threePointersAttempted": 0, "threePointersPercentage": 0.0, "freeThrowsMade": 0, "freeThrowsAttempted": 0, "freeThrowsPercentage": 0.0, "plusMinusPoints": -4.0}, {"personId": 1631207, "name": "Dalen Terry", "teamId": 1610612755, "tricode": "PHI", "position": "", "minutes": "1:14", "points": 0, "reboundsTotal": 0, "reboundsOffensive": 0, "reboundsDefensive": 0, "assists": 0, "steals": 0, "blocks": 0, "turnovers": 0, "foulsPersonal": 0, "fieldGoalsMade": 0, "fieldGoalsAttempted": 0, "fieldGoalsPercentage": 0.0, "threePointersMade": 0, "threePointersAttempted": 0, "threePointersPercentage": 0.0, "freeThrowsMade": 0, "freeThrowsAttempted": 0, "freeThrowsPercentage": 0.0, "plusMinusPoints": -4.0}, {"personId": 1641737, "name": "Adem Bona", "teamId": 1610612755, "tricode": "PHI", "position": "", "minutes": "1:14", "points": 0, "reboundsTotal": 0, "reboundsOffensive": 0, "reboundsDefensive": 0, "assists": 0, "steals": 0, "blocks": 0, "turnovers": 0, "foulsPersonal": 0, "fieldGoalsMade": 0, "fieldGoalsAttempted": 0, "fieldGoalsPercentage": 0.0, "threePointersMade": 0, "threePointersAttempted": 0, "threePointersPercentage": 0.0, "freeThrowsMade": 0, "freeThrowsAttempted": 0, "freeThrowsPercentage": 0.0, "plusMinusPoints": -4.0}, {"personId": 200768, "name": "Kyle Lowry", "teamId": 1610612755, "tricode": "PHI", "position": "", "minutes": "1:13", "points": 0, "reboundsTotal": 0, "reboundsOffensive": 0, "reboundsDefensive": 0, "assists": 0, "steals": 0, "blocks": 0, "turnovers": 0, "foulsPersonal": 0, "fieldGoalsMade": 0, "fieldGoalsAttempted": 0, "fieldGoalsPercentage": 0.0, "threePointersMade": 0, "threePointersAttempted": 0, "threePointersPercentage": 0.0, "freeThrowsMade": 0, "freeThrowsAttempted": 0, "freeThrowsPercentage": 0.0, "plusMinusPoints": -4.0}, {"personId": 1628369, "name": "Jayson Tatum", "teamId": 1610612738, "tricode": "BOS", "position": "F", "minutes": "28:48", "points": 17, "reboundsTotal": 11, "reboundsOffensive": 0, "reboundsDefensive": 11, "assists": 3, "steals": 0, "blocks": 0, "turnovers": 3, "foulsPersonal": 1, "fieldGoalsMade": 6, "fieldGoalsAttempted": 13, "fieldGoalsPercentage": 0.462, "threePointersMade": 2, "threePointersAttempted": 6, "threePointersPercentage": 0.333, "freeThrowsMade": 3, "freeThrowsAttempted": 5, "freeThrowsPercentage": 0.6, "plusMinusPoints": -11.0}, {"personId": 1630573, "name": "Sam Hauser", "teamId": 1610612738, "tricode": "BOS", "position": "F", "minutes": "20:58", "points": 5, "reboundsTotal": 4, "reboundsOffensive": 0, "reboundsDefensive": 4, "assists": 1, "steals": 0, "blocks": 0, "turnovers": 0, "foulsPersonal": 1, "fieldGoalsMade": 2, "fieldGoalsAttempted": 6, "fieldGoalsPercentage": 0.333, "threePointersMade": 1, "threePointersAttempted": 5, "threePointersPercentage": 0.2, "freeThrowsMade": 0, "freeThrowsAttempted": 0, "freeThrowsPercentage": 0.0, "plusMinusPoints": -12.0}, {"personId": 1629674, "name": "Neemias Queta", "teamId": 1610612738, "tricode": "BOS", "position": "C", "minutes": "20:18", "points": 4, "reboundsTotal": 11, "reboundsOffensive": 1, "reboundsDefensive": 10, "assists": 0, "steals": 0, "blocks": 2, "turnovers": 1, "foulsPersonal": 3, "fieldGoalsMade": 2, "fieldGoalsAttempted": 5, "fieldGoalsPercentage": 0.4, "threePointersMade": 0, "threePointersAttempted": 0, "threePointersPercentage": 0.0, "freeThrowsMade": 0, "freeThrowsAttempted": 0, "freeThrowsPercentage": 0.0, "plusMinusPoints": -14.0}, {"personId": 1627759, "name": "Jaylen Brown", "teamId": 1610612738, "tricode": "BOS", "position": "G", "minutes": "28:29", "points": 18, "reboundsTotal": 1, "reboundsOffensive": 0, "reboundsDefensive": 1, "assists": 2, "steals": 0, "blocks": 0, "turnovers": 5, "foulsPersonal": 4, "fieldGoalsMade": 7, "fieldGoalsAttempted": 17, "fieldGoalsPercentage": 0.412, "threePointersMade": 2, "threePointersAttempted": 6, "threePointersPercentage": 0.333, "freeThrowsMade": 2, "freeThrowsAttempted": 6, "freeThrowsPercentage": 0.333, "plusMinusPoints": -24.0}, {"personId": 1628401, "name": "Derrick White", "teamId": 1610612738, "tricode": "BOS", "position": "G", "minutes": "31:31", "points": 11, "reboundsTotal": 1, "reboundsOffensive": 1, "reboundsDefensive": 0, "assists": 1, "steals": 3, "blocks": 0, "turnovers": 2, "foulsPersonal": 3, "fieldGoalsMade": 3, "fieldGoalsAttempted": 8, "fieldGoalsPercentage": 0.375, "threePointersMade": 3, "threePointersAttempted": 6, "threePointersPercentage": 0.5, "freeThrowsMade": 2, "freeThrowsAttempted": 2, "freeThrowsPercentage": 1.0, "plusMinusPoints": -25.0}, {"personId": 1630202, "name": "Payton Pritchard", "teamId": 1610612738, "tricode": "BOS", "position": "", "minutes": "36:09", "points": 14, "reboundsTotal": 3, "reboundsOffensive": 0, "reboundsDefensive": 3, "assists": 5, "steals": 0, "blocks": 0, "turnovers": 1, "foulsPersonal": 0, "fieldGoalsMade": 6, "fieldGoalsAttempted": 16, "fieldGoalsPercentage": 0.375, "threePointersMade": 1, "threePointersAttempted": 8, "threePointersPercentage": 0.125, "freeThrowsMade": 1, "freeThrowsAttempted": 1, "freeThrowsPercentage": 1.0, "plusMinusPoints": -6.0}, {"personId": 202696, "name": "Nikola Vu\u010devi\u0107", "teamId": 1610612738, "tricode": "BOS", "position": "", "minutes": "14:09", "points": 2, "reboundsTotal": 2, "reboundsOffensive": 1, "reboundsDefensive": 1, "assists": 1, "steals": 1, "blocks": 0, "turnovers": 0, "foulsPersonal": 0, "fieldGoalsMade": 1, "fieldGoalsAttempted": 5, "fieldGoalsPercentage": 0.2, "threePointersMade": 0, "threePointersAttempted": 2, "threePointersPercentage": 0.0, "freeThrowsMade": 0, "freeThrowsAttempted": 0, "freeThrowsPercentage": 0.0, "plusMinusPoints": -5.0}, {"personId": 1641775, "name": "Jordan Walsh", "teamId": 1610612738, "tricode": "BOS", "position": "", "minutes": "19:18", "points": 3, "reboundsTotal": 5, "reboundsOffensive": 2, "reboundsDefensive": 3, "assists": 3, "steals": 0, "blocks": 1, "turnovers": 0, "foulsPersonal": 1, "fieldGoalsMade": 1, "fieldGoalsAttempted": 3, "fieldGoalsPercentage": 0.333, "threePointersMade": 0, "threePointersAttempted": 1, "threePointersPercentage": 0.0, "freeThrowsMade": 1, "freeThrowsAttempted": 2, "freeThrowsPercentage": 0.5, "plusMinusPoints": 10.0}, {"personId": 1630568, "name": "Luka Garza", "teamId": 1610612738, "tricode": "BOS", "position": "", "minutes": "13:33", "points": 9, "reboundsTotal": 2, "reboundsOffensive": 2, "reboundsDefensive": 0, "assists": 1, "steals": 0, "blocks": 0, "turnovers": 0, "foulsPersonal": 2, "fieldGoalsMade": 4, "fieldGoalsAttempted": 5, "fieldGoalsPercentage": 0.8, "threePointersMade": 1, "threePointersAttempted": 2, "threePointersPercentage": 0.5, "freeThrowsMade": 0, "freeThrowsAttempted": 0, "freeThrowsPercentage": 0.0, "plusMinusPoints": 6.0}, {"personId": 1631248, "name": "Baylor Scheierman", "teamId": 1610612738, "tricode": "BOS", "position": "", "minutes": "15:09", "points": 5, "reboundsTotal": 3, "reboundsOffensive": 0, "reboundsDefensive": 3, "assists": 1, "steals": 2, "blocks": 0, "turnovers": 1, "foulsPersonal": 2, "fieldGoalsMade": 2, "fieldGoalsAttempted": 4, "fieldGoalsPercentage": 0.5, "threePointersMade": 1, "threePointersAttempted": 3, "threePointersPercentage": 0.333, "freeThrowsMade": 0, "freeThrowsAttempted": 0, "freeThrowsPercentage": 0.0, "plusMinusPoints": 2.0}, {"personId": 1631199, "name": "Ron Harper Jr.", "teamId": 1610612738, "tricode": "BOS", "position": "", "minutes": "10:24", "points": 3, "reboundsTotal": 3, "reboundsOffensive": 1, "reboundsDefensive": 2, "assists": 0, "steals": 1, "blocks": 0, "turnovers": 0, "foulsPersonal": 1, "fieldGoalsMade": 1, "fieldGoalsAttempted": 3, "fieldGoalsPercentage": 0.333, "threePointersMade": 1, "threePointersAttempted": 2, "threePointersPercentage": 0.5, "freeThrowsMade": 0, "freeThrowsAttempted": 0, "freeThrowsPercentage": 0.0, "plusMinusPoints": 10.0}, {"personId": 1630625, "name": "Dalano Banton", "teamId": 1610612738, "tricode": "BOS", "position": "", "minutes": "1:14", "points": 2, "reboundsTotal": 0, "reboundsOffensive": 0, "reboundsDefensive": 0, "assists": 0, "steals": 0, "blocks": 0, "turnovers": 0, "foulsPersonal": 0, "fieldGoalsMade": 1, "fieldGoalsAttempted": 1, "fieldGoalsPercentage": 1.0, "threePointersMade": 0, "threePointersAttempted": 0, "threePointersPercentage": 0.0, "freeThrowsMade": 0, "freeThrowsAttempted": 0, "freeThrowsPercentage": 0.0, "plusMinusPoints": 4.0}]}